zlic.pyi
zlic.cpython-36m-x86_64-linux-gnu.so
zlic.cpython-310-x86_64-linux-gnu.so
pyzlic-1.5.0.dist-info/top_level.txt
pyzlic-1.5.0.dist-info/zip-safe
pyzlic-1.5.0.dist-info/RECORD
pyzlic-1.5.0.dist-info/METADATA
pyzlic-1.5.0.dist-info/WHEEL
pyzlic-1.5.0.data/scripts/pyzlic
